[
  {
	"ScenePath": "res://Cenas/Mob.tscn",
	"SpriteSheetRows": 2,
	"SpriteSheetCols": 4,
	"SpriteSheetWidth": 400,
	"SpriteSheetHeight": 150,
	"SpriteSheetPath": "res://Sprites/javali_spritesheet.png",
	"Position": [1235, 210],
	"FrameWidth": 100,
	"FrameHeight": 75,
	"AiEnabled": true
  },
  {
	"ScenePath": "res://Cenas/StaticNpc.tscn",
	"SpriteSheetRows": 1,
	"SpriteSheetCols": 2,
	"SpriteSheetWidth": 150,
	"SpriteSheetHeight": 77,
	"DialogTimelineName": "npc_dialogo_2",
	"CharacterResourcePath": "res://Chars/Athena.dch",
	"PlayerResourcePath": "res://Chars/Odisseu.dch",
	"SpriteSheetPath": "res://Sprites/athena_spritesheet.png",
	"Position": [615, 145]
  },
  {
	"ScenePath": "res://Cenas/StaticNpc.tscn",
	"DialogStyle": "",
	"SpriteSheetRows": 1,
	"SpriteSheetCols": 1,
	"SpriteSheetWidth": 150,
	"SpriteSheetHeight": 77,
	"DialogTimelineName": "npc_dialogo_2",
	"CharacterResourcePath": "res://Chars/Athena.dch",
	"PlayerResourcePath": "res://Chars/Odisseu.dch",
	"SpriteSheetPath": "res://Sprites/npc_teste.png",
	"Position": [400, 300]
  },
  {
	"ScenePath": "res://Cenas/StaticNpc.tscn",
	"DialogStyle": "",
	"SpriteSheetRows": 1,
	"SpriteSheetCols": 1,
	"SpriteSheetWidth": 150,
	"SpriteSheetHeight": 77,
	"DialogTimelineName": "npc_dialogo_2",
	"CharacterResourcePath": "res://Chars/Athena.dch",
	"PlayerResourcePath": "res://Chars/Odisseu.dch",
	"SpriteSheetPath": "res://Sprites/npc_teste.png",
	"Position": [480, 300]
  },
  {
	"ScenePath": "res://Cenas/StaticNpc.tscn",
	"DialogStyle": "",
	"SpriteSheetRows": 1,
	"SpriteSheetCols": 1,
	"SpriteSheetWidth": 150,
	"SpriteSheetHeight": 77,
	"DialogTimelineName": "npc_dialogo_2",
	"CharacterResourcePath": "res://Chars/Athena.dch",
	"PlayerResourcePath": "res://Chars/Odisseu.dch",
	"SpriteSheetPath": "res://Sprites/npc_teste.png",
	"Position": [400, 380]
  },
  {
	"ScenePath": "res://Cenas/StaticNpc.tscn",
	"DialogStyle": "",
	"SpriteSheetRows": 1,
	"SpriteSheetCols": 1,
	"SpriteSheetWidth": 150,
	"SpriteSheetHeight": 77,
	"DialogTimelineName": "npc_dialogo_2",
	"CharacterResourcePath": "res://Chars/Athena.dch",
	"PlayerResourcePath": "res://Chars/Odisseu.dch",
	"SpriteSheetPath": "res://Sprites/npc_teste.png",
	"Position": [480, 380]
  },
  {
	"ScenePath": "res://Cenas/StaticNpc.tscn",
	"DialogStyle": "",
	"SpriteSheetRows": 1,
	"SpriteSheetCols": 1,
	"SpriteSheetWidth": 150,
	"SpriteSheetHeight": 77,
	"DialogTimelineName": "npc_dialogo_2",
	"CharacterResourcePath": "res://Chars/Athena.dch",
	"PlayerResourcePath": "res://Chars/Odisseu.dch",
	"SpriteSheetPath": "res://Sprites/npc_teste.png",
	"Position": [440, 460]
  },
  {
	"ScenePath": "res://Cenas/StaticNpc.tscn",
	"DialogStyle": "",
	"SpriteSheetRows": 1,
	"SpriteSheetCols": 1,
	"SpriteSheetWidth": 150,
	"SpriteSheetHeight": 77,
	"DialogTimelineName": "npc_dialogo_2",
	"CharacterResourcePath": "res://Chars/Athena.dch",
	"PlayerResourcePath": "res://Chars/Odisseu.dch",
	"SpriteSheetPath": "res://Sprites/npc_teste.png",
	"Position": [520, 460]
  },
  {
	"ScenePath": "res://Cenas/StaticNpc.tscn",
	"DialogStyle": "",
	"SpriteSheetRows": 1,
	"SpriteSheetCols": 1,
	"SpriteSheetWidth": 150,
	"SpriteSheetHeight": 77,
	"DialogTimelineName": "npc_dialogo_2",
	"CharacterResourcePath": "res://Chars/Athena.dch",
	"PlayerResourcePath": "res://Chars/Odisseu.dch",
	"SpriteSheetPath": "res://Sprites/npc_teste.png",
	"Position": [440, 540]
  },
  {
	"ScenePath": "res://Cenas/Player.tscn",
	"Position": [600, 350],
	"BaseSpeed": 200,
	"PlayerSpriteSheetPath": "res://Sprites/player_spritesheet.png",
	"SpriteHFrames": 8,
	"SpriteVFrames": 9,
	"CrosshairPath": "res://Sprites/crosshair.png",
	"ArrowScenePath": "res://Cenas/Arrow.tscn",
	"ArrowSpriteSheetPath": "res://Sprites/arrow.png",
	"AttackSpriteSheetPath": "res://Sprites/attack_spritesheet.png",
	"AttackHFrames": 5,
	"AttackVFrames": 8,
	"AttackFrameWidth": 96,
	"AttackFrameHeight": 60
  }
]
